rawpy-0.25.1.dist-info/RECORD
rawpy-0.25.1.dist-info/WHEEL
rawpy-0.25.1.dist-info/top_level.txt
rawpy-0.25.1.dist-info/METADATA
rawpy-0.25.1.dist-info/licenses/LICENSE.LibRaw
rawpy-0.25.1.dist-info/licenses/LICENSE
rawpy/_rawpy.cpython-313-darwin.so
rawpy/_version.py
rawpy/enhance.py
rawpy/__init__.py
rawpy/.dylibs/liblcms2.2.dylib
rawpy/.dylibs/libjpeg.9.dylib
rawpy/.dylibs/libjasper.7.0.0.dylib
rawpy/.dylibs/libraw_r.23.0.0.dylib
